openfisca_ceq/__init__.py
openfisca_ceq/entities.py
openfisca_ceq/assets/README.md
openfisca_ceq/assets/merged.csv
openfisca_ceq/assets/merged.xls
openfisca_ceq/assets/merged_by_coicop.xlsx
openfisca_ceq/assets/unit_cost_of_education_public_service_by_country.csv
openfisca_ceq/assets/unit_cost_of_education_public_service_by_country_ministry_of_education_numbers.csv
openfisca_ceq/tests/__init__.py
openfisca_ceq/tests/test_calibration.py
openfisca_ceq/tests/test_indirect_tax_variables_generator.py
openfisca_ceq/tests/test_input_data.py
openfisca_ceq/tests/test_survey_scenario.py
openfisca_ceq/tests/tests_data_dtypes.py
openfisca_ceq/tests/formulas/final_income.yaml
openfisca_ceq/tests/formulas/market_income.yaml
openfisca_ceq/tools/__init__.py
openfisca_ceq/tools/data_ceq_correspondence.py
openfisca_ceq/tools/survey_scenario.py
openfisca_ceq/tools/tax_benefit_system_ceq_completion.py
openfisca_ceq/tools/data/__init__.py
openfisca_ceq/tools/data/education_unit_cost.py
openfisca_ceq/tools/data/expenditures_loader.py
openfisca_ceq/tools/data/income_loader.py
openfisca_ceq/tools/data/income_targets.py
openfisca_ceq/tools/data/tax_targets.py
openfisca_ceq/tools/indirect_taxation/__init__.py
openfisca_ceq/tools/indirect_taxation/consumption_items_nomenclature.py
openfisca_ceq/tools/indirect_taxation/tax_benefit_system_indirect_taxation_completion.py
openfisca_ceq/tools/indirect_taxation/variables_generator.py
openfisca_ceq/tools/results/__init__.py
openfisca_ceq/tools/results/imports.py
openfisca_ceq/tools/results/inequality.py
openfisca_ceq/tools/results/taxes.py
openfisca_ceq/variables/contributions.py
openfisca_ceq/variables/income.py
openfisca_ceq/variables/statistics.py
openfisca_ceq/variables/subsidies.py
openfisca_ceq/variables/taxes.py
openfisca_ceq/variables/transfers/cash_transfers.py
openfisca_ceq/variables/transfers/in_kind_transfers.py
OpenFisca_CEQ-0.4.1.dist-info/LICENSE.AGPL.txt
OpenFisca_CEQ-0.4.1.dist-info/METADATA
OpenFisca_CEQ-0.4.1.dist-info/WHEEL
OpenFisca_CEQ-0.4.1.dist-info/top_level.txt
OpenFisca_CEQ-0.4.1.dist-info/RECORD
